Workbook

Sheet Assumptions
A1: ASSUMPTIONS
A2: Key Model Inputs
B3: 2024 | C3: 2025 | D3: 2026 | E3: 2027 | F3: 2028 | G3: 2029 | H3: 2030 | I3: 2031 | J3: 2032 | K3: 2033
A4: Revenue Growth Rate | B4: 0.15 | C4: 0.12 | D4: 0.1 | E4: 0.08 | F4: 0.07 | G4: 0.06 | H4: 0.05 | I4: 0.05 | J4: 0.04 | K4: 0.04
A5: COGS % of Revenue | B5: 0.42 | C5: 0.41 | D5: 0.4 | E5: 0.39 | F5: 0.38 | G5: 0.38 | H5: 0.37 | I5: 0.37 | J5: 0.36 | K5: 0.36
A6: SGA % of Revenue | B6: 0.18 | C6: 0.17 | D6: 0.16 | E6: 0.15 | F6: 0.15 | G6: 0.14 | H6: 0.14 | I6: 0.13 | J6: 0.13 | K6: 0.13
A7: R&D % of Revenue | B7: 0.12 | C7: 0.11 | D7: 0.1 | E7: 0.1 | F7: 0.09 | G7: 0.09 | H7: 0.08 | I7: 0.08 | J7: 0.08 | K7: 0.08
A8: D&A % of Revenue | B8: 0.03 | C8: 0.03 | D8: 0.03 | E8: 0.03 | F8: 0.03 | G8: 0.03 | H8: 0.03 | I8: 0.03 | J8: 0.03 | K8: 0.03
A9: Tax Rate | B9: 0.21 | C9: 0.21 | D9: 0.21 | E9: 0.21 | F9: 0.21 | G9: 0.21 | H9: 0.21 | I9: 0.21 | J9: 0.21 | K9: 0.21
A10: CapEx % of Revenue | B10: 0.05 | C10: 0.05 | D10: 0.04 | E10: 0.04 | F10: 0.04 | G10: 0.03 | H10: 0.03 | I10: 0.03 | J10: 0.03 | K10: 0.03
A11: NWC % of Revenue | B11: 0.1 | C11: 0.1 | D11: 0.09 | E11: 0.09 | F11: 0.09 | G11: 0.08 | H11: 0.08 | I11: 0.08 | J11: 0.08 | K11: 0.08
A12: WACC | B12: 0.1 | C12: 0.1 | D12: 0.1 | E12: 0.1 | F12: 0.1 | G12: 0.1 | H12: 0.1 | I12: 0.1 | J12: 0.1 | K12: 0.1
A13: Terminal Growth Rate | B13: 0.025 | C13: 0.025 | D13: 0.025 | E13: 0.025 | F13: 0.025 | G13: 0.025 | H13: 0.025 | I13: 0.025 | J13: 0.025 | K13: 0.025
A14: Shares Outstanding (M) | B14: 100 | C14: 100 | D14: 100 | E14: 100 | F14: 100 | G14: 100 | H14: 100 | I14: 100 | J14: 100 | K14: 100
A15: Interest Rate on Debt | B15: 0.045 | C15: 0.045 | D15: 0.045 | E15: 0.045 | F15: 0.045 | G15: 0.045 | H15: 0.045 | I15: 0.045 | J15: 0.045 | K15: 0.045
A16: Dividend Payout Ratio | B16: 0.3 | C16: 0.3 | D16: 0.3 | E16: 0.3 | F16: 0.3 | G16: 0.3 | H16: 0.3 | I16: 0.3 | J16: 0.3 | K16: 0.3

Sheet Revenue
A1: REVENUE BUILD
B3: 2024 | C3: 2025 | D3: 2026 | E3: 2027 | F3: 2028 | G3: 2029 | H3: 2030 | I3: 2031 | J3: 2032 | K3: 2033
A4: Product A - Enterprise SaaS | B4: 50000000 | C4: =B4*(1+Assumptions!C$4) | D4: =C4*(1+Assumptions!D$4) | E4: =D4*(1+Assumptions!E$4) | F4: 99999999 | G4: =F4*(1+Assumptions!G$4) | H4: =G4*(1+Assumptions!H$4) | I4: =H4*(1+Assumptions!I$4) | J4: =I4*(1+Assumptions!J$4) | K4: =J4*(1+Assumptions!K$4)
A5: Product B - SMB Platform | B5: 25000000 | C5: =B5*(1+Assumptions!C$4) | D5: =C5*(1+Assumptions!D$4) | E5: =D5*(1+Assumptions!E$4) | F5: =E5*(1+Assumptions!F$4) | G5: =F5*(1+Assumptions!G$4) | H5: =G5*(1+Assumptions!H$4) | I5: =H5*(1+Assumptions!I$4) | J5: =I5*(1+Assumptions!J$4) | K5: =J5*(1+Assumptions!K$4)
A6: Product C - Data Analytics | B6: 15000000 | C6: =B6*(1+Assumptions!C$4) | D6: =C6*(1+Assumptions!D$4) | E6: =D6*(1+Assumptions!E$4) | F6: =E6*(1+Assumptions!F$4) | G6: =F6*(1+Assumptions!G$4) | H6: =G6*(1+Assumptions!H$4) | I6: =H6*(1+Assumptions!I$4) | J6: =I6*(1+Assumptions!J$4) | K6: =J6*(1+Assumptions!K$4)
A7: Product D - Cloud Services | B7: 10000000 | C7: =B7*(1+Assumptions!C$4) | D7: =C7*(1+Assumptions!D$4) | E7: =D7*(1+Assumptions!E$4) | F7: =E7*(1+Assumptions!F$4) | G7: =F7*(1+Assumptions!G$4) | H7: =G7*(1+Assumptions!H$4) | I7: =H7*(1+Assumptions!I$4) | J7: =I7*(1+Assumptions!J$4) | K7: =J7*(1+Assumptions!K$4)
A8: Professional Services | B8: 8000000 | C8: =B8*(1+Assumptions!C$4) | D8: =C8*(1+Assumptions!D$4) | E8: =D8*(1+Assumptions!E$4) | F8: =E8*(1+Assumptions!F$4) | G8: =F8*(1+Assumptions!G$4) | H8: =G8*(1+Assumptions!H$4) | I8: =H8*(1+Assumptions!I$4) | J8: =I8*(1+Assumptions!J$4) | K8: =J8*(1+Assumptions!K$4)
A9: Maintenance & Support | B9: 5000000 | C9: =B9*(1+Assumptions!C$4) | D9: =C9*(1+Assumptions!D$4) | E9: =D9*(1+Assumptions!E$4) | F9: =E9*(1+Assumptions!F$4) | G9: =F9*(1+Assumptions!G$4) | H9: =G9*(1+Assumptions!H$4) | I9: =H9*(1+Assumptions!I$4) | J9: =I9*(1+Assumptions!J$4) | K9: =J9*(1+Assumptions!K$4)
A10: Licensing | B10: 3000000 | C10: =B10*(1+Assumptions!C$4) | D10: =C10*(1+Assumptions!D$4) | E10: =D10*(1+Assumptions!E$4) | F10: =E10*(1+Assumptions!F$4) | G10: =F10*(1+Assumptions!G$4) | H10: =G10*(1+Assumptions!H$4) | I10: =H10*(1+Assumptions!I$4) | J10: =I10*(1+Assumptions!J$4) | K10: =J10*(1+Assumptions!K$4)
A11: Other Revenue | B11: 2000000 | C11: =B11*(1+Assumptions!C$4) | D11: =C11*(1+Assumptions!D$4) | E11: =D11*(1+Assumptions!E$4) | F11: =E11*(1+Assumptions!F$4) | G11: =F11*(1+Assumptions!G$4) | H11: =G11*(1+Assumptions!H$4) | I11: =H11*(1+Assumptions!I$4) | J11: =I11*(1+Assumptions!J$4) | K11: =J11*(1+Assumptions!K$4)
A13: Total Revenue | B13: =SUM(B4:B11) | C13: =SUM(C4:C11) | D13: =SUM(D4:D11) | E13: =SUM(E4:E11) | F13: =SUM(F4:F11) | G13: =SUM(G4:G11) | H13: =SUM(H4:H11) | I13: =SUM(I4:I11) | ... K13: =SUM(K4:K11)

Sheet COGS
A1: COST OF GOODS SOLD
B3: 2024 | C3: 2025 | D3: 2026 | E3: 2027 | F3: 2028 | G3: 2029 | H3: 2030 | I3: 2031 | J3: 2032 | K3: 2033
A4: Cloud Hosting & Infrastructure | B4: =Revenue!B$13*Assumptions!B$5*0.2 | C4: =Revenue!C$13*Assumptions!C$5*0.2 | D4: =Revenue!D$13*Assumptions!D$5*0.2 | E4: =Revenue!E$13*Assumptions!E$5*0.2 | F4: =Revenue!F$13*Assumptions!F$5*0.2 | G4: =Revenue!G$13*Assumptions!G$5*0.2 | H4: =Revenue!H$13*Assumptions!H$5*0.2 | I4: =Revenue!I$13*Assumptions!I$5*0.2 | ... K4: =Revenue!K$13*Assumptions!K$5*0.2
A5: Software Licenses (3rd party) | B5: =Revenue!B$13*Assumptions!B$5*0.2 | C5: =Revenue!C$13*Assumptions!C$5*0.2 | D5: =Revenue!D$13*Assumptions!D$5*0.2 | E5: =Revenue!E$13*Assumptions!E$5*0.2 | F5: =Revenue!F$13*Assumptions!F$5*0.2 | G5: =Revenue!G$13*Assumptions!G$5*0.2 | H5: =Revenue!H$13*Assumptions!H$5*0.2 | I5: =Revenue!I$13*Assumptions!I$5*0.2 | ... K5: =Revenue!K$13*Assumptions!K$5*0.2
A6: Customer Support Staff | B6: =Revenue!B$13*Assumptions!B$5*0.2 | C6: =Revenue!C$13*Assumptions!C$5*0.2 | D6: =Revenue!D$13*Assumptions!D$5*0.2 | E6: =Revenue!E$13*Assumptions!E$5*0.2 | F6: =Revenue!F$13*Assumptions!F$5*0.2 | G6: =Revenue!G$13*Assumptions!G$5*0.2 | H6: =Revenue!H$13*Assumptions!H$5*0.2 | I6: =Revenue!I$13*Assumptions!I$5*0.2 | ... K6: =Revenue!K$13*Assumptions!K$5*0.2
A7: Payment Processing Fees | B7: =Revenue!B$13*Assumptions!B$5*0.2 | C7: =Revenue!C$13*Assumptions!C$5*0.2 | D7: =Revenue!D$13*Assumptions!D$5*0.2 | E7: =Revenue!E$13*Assumptions!E$5*0.2 | F7: =Revenue!F$13*Assumptions!F$5*0.2 | G7: =Revenue!G$13*Assumptions!G$5*0.2 | H7: =Revenue!H$13*Assumptions!H$5*0.2 | I7: =Revenue!I$13*Assumptions!I$5*0.2 | ... K7: =Revenue!K$13*Assumptions!K$5*0.2
A8: Data Center Operations | B8: =Revenue!B$13*Assumptions!B$5*0.2 | C8: =Revenue!C$13*Assumptions!C$5*0.2 | D8: =Revenue!D$13*Assumptions!D$5*0.2 | E8: =Revenue!E$13*Assumptions!E$5*0.2 | F8: =Revenue!F$13*Assumptions!F$5*0.2 | G8: =Revenue!G$13*Assumptions!G$5*0.2 | H8: =Revenue!H$13*Assumptions!H$5*0.2 | I8: =Revenue!I$13*Assumptions!I$5*0.2 | ... K8: =Revenue!K$13*Assumptions!K$5*0.2
A10: Total COGS | B10: =SUM(B4:B8) | C10: =SUM(C4:C8) | D10: =SUM(D4:D8) | E10: =SUM(E4:E8) | F10: =SUM(F4:F8) | G10: =SUM(G4:G8) | H10: =SUM(H4:H8) | I10: =SUM(I4:I8) | ... K10: =SUM(K4:K8)

Sheet OpEx
A1: OPERATING EXPENSES
B3: 2024 | C3: 2025 | D3: 2026 | E3: 2027 | F3: 2028 | G3: 2029 | H3: 2030 | I3: 2031 | J3: 2032 | K3: 2033
A4: Sales & Marketing | B4: =Revenue!B$13*Assumptions!B$6*0.35 | C4: =Revenue!C$13*Assumptions!C$6*0.35 | D4: =Revenue!D$13*Assumptions!D$6*0.35 | E4: =Revenue!E$13*Assumptions!E$6*0.35 | F4: =Revenue!F$13*Assumptions!F$6*0.35 | G4: =Revenue!G$13*Assumptions!G$6*0.35 | H4: =Revenue!H$13*Assumptions!H$6*0.35 | I4: =Revenue!I$13*Assumptions!I$6*0.35 | ... K4: =Revenue!K$13*Assumptions!K$6*0.35
A5: Salaries & Wages | B5: =Revenue!B$13*Assumptions!B$6*0.25 | C5: =Revenue!C$13*Assumptions!C$6*0.25 | D5: =Revenue!D$13*Assumptions!D$6*0.25 | E5: =Revenue!E$13*Assumptions!E$6*0.25 | F5: =Revenue!F$13*Assumptions!F$6*0.25 | G5: =Revenue!G$13*Assumptions!G$6*0.25 | H5: =Revenue!H$13*Assumptions!H$6*0.25 | I5: =Revenue!I$13*Assumptions!I$6*0.25 | ... K5: =Revenue!K$13*Assumptions!K$6*0.25
A6: Research & Development | B6: =Revenue!B$13*Assumptions!B$7*0.6 | C6: =Revenue!C$13*Assumptions!C$7*0.6 | D6: =Revenue!D$13*Assumptions!D$7*0.6 | E6: =Revenue!E$13*Assumptions!E$7*0.6 | F6: =Revenue!F$13*Assumptions!F$7*0.6 | G6: =Revenue!G$13*Assumptions!G$7*0.6 | H6: =Revenue!H$13*Assumptions!H$7*0.6 | I6: =Revenue!I$13*Assumptions!I$7*0.6 | ... K6: =Revenue!K$13*Assumptions!K$7*0.6
A7: General & Administrative | B7: =Revenue!B$13*Assumptions!B$6*0.1 | C7: =Revenue!C$13*Assumptions!C$6*0.1 | D7: =Revenue!D$13*Assumptions!D$6*0.1 | E7: =Revenue!E$13*Assumptions!E$6*0.1 | F7: =Revenue!F$13*Assumptions!F$6*0.1 | G7: =Revenue!G$13*Assumptions!G$6*0.1 | H7: =Revenue!H$13*Assumptions!H$6*0.1 | I7: =Revenue!I$13*Assumptions!I$6*0.1 | ... K7: =Revenue!K$13*Assumptions!K$6*0.1
A8: Depreciation & Amortization | B8: =Revenue!B$13*Assumptions!B$8*1.0 | C8: =Revenue!C$13*Assumptions!C$8*1.0 | D8: =Revenue!D$13*Assumptions!D$8*1.0 | E8: =Revenue!E$13*Assumptions!E$8*1.0 | F8: =Revenue!F$13*Assumptions!F$8*1.0 | G8: =Revenue!G$13*Assumptions!G$8*1.0 | H8: =Revenue!H$13*Assumptions!H$8*1.0 | I8: =Revenue!I$13*Assumptions!I$8*1.0 | ... K8: =Revenue!K$13*Assumptions!K$8*1.0
A9: Rent & Facilities | B9: =Revenue!B$13*Assumptions!B$6*0.08 | C9: =Revenue!C$13*Assumptions!C$6*0.08 | D9: =Revenue!D$13*Assumptions!D$6*0.08 | E9: =Revenue!E$13*Assumptions!E$6*0.08 | F9: =Revenue!F$13*Assumptions!F$6*0.08 | G9: =Revenue!G$13*Assumptions!G$6*0.08 | H9: =Revenue!H$13*Assumptions!H$6*0.08 | I9: =Revenue!I$13*Assumptions!I$6*0.08 | ... K9: =Revenue!K$13*Assumptions!K$6*0.08
A10: Travel & Entertainment | B10: =Revenue!B$13*Assumptions!B$6*0.05 | C10: =Revenue!C$13*Assumptions!C$6*0.05 | D10: =Revenue!D$13*Assumptions!D$6*0.05 | E10: =Revenue!E$13*Assumptions!E$6*0.05 | F10: =Revenue!F$13*Assumptions!F$6*0.05 | G10: =Revenue!G$13*Assumptions!G$6*0.05 | H10: =Revenue!H$13*Assumptions!H$6*0.05 | I10: =Revenue!I$13*Assumptions!I$6*0.05 | ... K10: =Revenue!K$13*Assumptions!K$6*0.05
A11: Professional Fees (Legal, Audit) | B11: =Revenue!B$13*Assumptions!B$6*0.07 | C11: =Revenue!C$13*Assumptions!C$6*0.07 | D11: =Revenue!D$13*Assumptions!D$6*0.07 | E11: =Revenue!E$13*Assumptions!E$6*0.07 | F11: =Revenue!F$13*Assumptions!F$6*0.07 | G11: =Revenue!G$13*Assumptions!G$6*0.07 | H11: =Revenue!H$13*Assumptions!H$6*0.07 | I11: =Revenue!I$13*Assumptions!I$6*0.07 | ... K11: =Revenue!K$13*Assumptions!K$6*0.07
A12: Insurance | B12: =Revenue!B$13*Assumptions!B$6*0.05 | C12: =Revenue!C$13*Assumptions!C$6*0.05 | D12: =Revenue!D$13*Assumptions!D$6*0.05 | E12: =Revenue!E$13*Assumptions!E$6*0.05 | F12: =Revenue!F$13*Assumptions!F$6*0.05 | G12: =Revenue!G$13*Assumptions!G$6*0.05 | H12: =Revenue!H$13*Assumptions!H$6*0.05 | I12: =Revenue!I$13*Assumptions!I$6*0.05 | ... K12: =Revenue!K$13*Assumptions!K$6*0.05
A13: IT & Software | B13: =Revenue!B$13*Assumptions!B$7*0.4 | C13: =Revenue!C$13*Assumptions!C$7*0.4 | D13: =Revenue!D$13*Assumptions!D$7*0.4 | E13: =Revenue!E$13*Assumptions!E$7*0.4 | F13: =Revenue!F$13*Assumptions!F$7*0.4 | G13: =Revenue!G$13*Assumptions!G$7*0.4 | H13: =Revenue!H$13*Assumptions!H$7*0.4 | I13: =Revenue!I$13*Assumptions!I$7*0.4 | ... K13: =Revenue!K$13*Assumptions!K$7*0.4
A15: Total OpEx | B15: =SUM(B4:B13) | C15: =SUM(C4:C13) | D15: =SUM(D4:D13) | E15: =SUM(E4:E13) | F15: =SUM(F4:F13) | G15: =SUM(G4:G13) | H15: =SUM(H4:H13) | I15: =SUM(I4:I13) | ... K15: =SUM(K4:K13)

Sheet P&L
A1: PROFIT & LOSS STATEMENT
B3: 2024 | C3: 2025 | D3: 2026 | E3: 2027 | F3: 2028 | G3: 2029 | H3: 2030 | I3: 2031 | J3: 2032 | K3: 2033
A4: Revenue | B4: =Revenue!B$13 | C4: =Revenue!C$13 | D4: =Revenue!D$13 | E4: =Revenue!E$13 | F4: =Revenue!F$13 | G4: =Revenue!G$13 | H4: =Revenue!H$13 | I4: =Revenue!I$13 | ... K4: =Revenue!K$13
A5: Cost of Goods Sold | B5: =-COGS!B$10 | C5: =-COGS!C$10 | D5: =-COGS!D$10 | E5: =-COGS!E$10 | F5: =-COGS!F$10 | G5: =-COGS!G$10 | H5: =-COGS!H$10 | I5: =-COGS!I$10 | ... K5: =-COGS!K$10
A6: Gross Profit | B6: =B4+B5 | C6: =C4+C5 | D6: =D4+D5 | E6: =E4+E5 | F6: =F4+F5 | G6: =G4+G5 | H6: =H4+H5 | I6: =I4+I5 | ... K6: =K4+K5
A7: Gross Margin | B7: =B6/B4 | C7: =C6/C4 | D7: =D6/D4 | E7: =E6/E4 | F7: =F6/F4 | G7: =G6/G4 | H7: =H6/H4 | I7: =I6/I4 | ... K7: =K6/K4
A9: Operating Expenses | B9: =-OpEx!B$15 | C9: =-OpEx!C$15 | D9: =-OpEx!D$15 | E9: =-OpEx!E$15 | F9: =-OpEx!F$15 | G9: =-OpEx!G$15 | H9: =-OpEx!H$15 | I9: =-OpEx!I$15 | ... K9: =-OpEx!K$15
A10: EBIT | B10: =B6+B9 | C10: =C6+C9 | D10: =D6+D9 | E10: =E6+E9 | F10: =F6+F9 | G10: =G6+G9 | H10: =H6+H9 | I10: =I6+I9 | ... K10: =K6+K9
A11: EBIT Margin | B11: =B10/B4 | C11: =C10/C4 | D11: =D10/D4 | E11: =E10/E4 | F11: =F10/F4 | G11: =G10/G4 | H11: =H10/H4 | I11: =I10/I4 | ... K11: =K10/K4
A13: Interest Expense | B13: =-'Balance Sheet'!B$16*Assumptions!B$15 | C13: =-'Balance Sheet'!C$16*Assumptions!C$15 | D13: =-'Balance Sheet'!D$16*Assumptions!D$15 | E13: =-'Balance Sheet'!E$16*Assumptions!E$15 | F13: =-'Balance Sheet'!F$16*Assumptions!F$15 | G13: =-'Balance Sheet'!G$16*Assumptions!G$15 | H13: =-'Balance Sheet'!H$16*Assumptions!H$15 | I13: =-'Balance Sheet'!I$16*Assumptions!I$15 | ... K13: =-'Balance Sheet'!K$16*Assumptions!K$15
A14: EBT | B14: =B10+B13 | C14: =C10+C13 | D14: =D10+D13 | E14: =E10+E13 | F14: =F10+F13 | G14: =G10+G13 | H14: =H10+H13 | I14: =I10+I13 | ... K14: =K10+K13
A15: Income Tax | B15: =-MAX(0,B14*Assumptions!B$9) | C15: =-MAX(0,C14*Assumptions!C$9) | D15: =-MAX(0,D14*Assumptions!D$9) | E15: =-MAX(0,E14*Assumptions!E$9) | F15: =-MAX(0,F14*Assumptions!F$9) | G15: =-MAX(0,G14*Assumptions!G$9) | H15: =-MAX(0,H14*Assumptions!H$9) | I15: =-MAX(0,I14*Assumptions!I$9) | ... K15: =-MAX(0,K14*Assumptions!K$9)
A16: Net Income | B16: =B14+B15 | C16: =C14+C15 | D16: =D14+D15 | E16: =E14+E15 | F16: =F14+F15 | G16: =G14+G15 | H16: =H14+H15 | I16: =I14+I15 | ... K16: =K14+K15
A17: Net Margin | B17: =B16/B4 | C17: =C16/C4 | D17: =D16/D4 | E17: =E16/E4 | F17: =F16/F4 | G17: =G16/G4 | H17: =H16/H4 | I17: =I16/I4 | ... K17: =K16/K4
A19: EPS | B19: =B16/Assumptions!B$14/1000000 | C19: =C16/Assumptions!C$14/1000000 | D19: =D16/Assumptions!D$14/1000000 | E19: =E16/Assumptions!E$14/1000000 | F19: =F16/Assumptions!F$14/1000000 | G19: =G16/Assumptions!G$14/1000000 | H19: =H16/Assumptions!H$14/1000000 | I19: =I16/Assumptions!I$14/1000000 | ... K19: =K16/Assumptions!K$14/1000000

Sheet Balance Sheet
A1: BALANCE SHEET
B3: 2024 | C3: 2025 | D3: 2026 | E3: 2027 | F3: 2028 | G3: 2029 | H3: 2030 | I3: 2031 | J3: 2032 | K3: 2033
A4: ASSETS
A5: Cash & Equivalents | B5: 50000000 | C5: ='Cash Flow'!C$19 | D5: ='Cash Flow'!D$19 | E5: ='Cash Flow'!E$19 | F5: ='Cash Flow'!F$19 | G5: ='Cash Flow'!G$19 | H5: ='Cash Flow'!H$19 | I5: ='Cash Flow'!I$19 | J5: ='Cash Flow'!J$19 | K5: ='Cash Flow'!K$19
A6: Accounts Receivable | B6: =Revenue!B$13*Assumptions!B$11*0.4 | C6: =Revenue!C$13*Assumptions!C$11*0.4 | D6: =Revenue!D$13*Assumptions!D$11*0.4 | E6: =Revenue!E$13*Assumptions!E$11*0.4 | F6: =Revenue!F$13*Assumptions!F$11*0.4 | G6: =Revenue!G$13*Assumptions!G$11*0.4 | H6: =Revenue!H$13*Assumptions!H$11*0.4 | I6: =Revenue!I$13*Assumptions!I$11*0.4 | ... K6: =Revenue!K$13*Assumptions!K$11*0.4
A7: Inventory | B7: =Revenue!B$13*Assumptions!B$11*0.3 | C7: =Revenue!C$13*Assumptions!C$11*0.3 | D7: =Revenue!D$13*Assumptions!D$11*0.3 | E7: =Revenue!E$13*Assumptions!E$11*0.3 | F7: =Revenue!F$13*Assumptions!F$11*0.3 | G7: =Revenue!G$13*Assumptions!G$11*0.3 | H7: =Revenue!H$13*Assumptions!H$11*0.3 | I7: =Revenue!I$13*Assumptions!I$11*0.3 | ... K7: =Revenue!K$13*Assumptions!K$11*0.3
A8: Prepaid Expenses | B8: =Revenue!B$13*0.02 | C8: =Revenue!C$13*0.02 | D8: =Revenue!D$13*0.02 | E8: =Revenue!E$13*0.02 | F8: =Revenue!F$13*0.02 | G8: =Revenue!G$13*0.02 | H8: =Revenue!H$13*0.02 | I8: =Revenue!I$13*0.02 | ... K8: =Revenue!K$13*0.02
A9: Total Current Assets | B9: =SUM(B5:B8) | C9: =SUM(C5:C8) | D9: =SUM(D5:D8) | E9: =SUM(E5:E8) | F9: =SUM(F5:F8) | G9: =SUM(G5:G8) | H9: =SUM(H5:H8) | I9: =SUM(I5:I8) | ... K9: =SUM(K5:K8)
A10: PP&E (Net) | B10: 30000000 | C10: =B10+Revenue!C$13*Assumptions!C$10-Revenue!C$13*Assumptions!C$8 | D10: =C10+Revenue!D$13*Assumptions!D$10-Revenue!D$13*Assumptions!D$8 | E10: =D10+Revenue!E$13*Assumptions!E$10-Revenue!E$13*Assumptions!E$8 | F10: =E10+Revenue!F$13*Assumptions!F$10-Revenue!F$13*Assumptions!F$8 | G10: =F10+Revenue!G$13*Assumptions!G$10-Revenue!G$13*Assumptions!G$8 | H10: =G10+Revenue!H$13*Assumptions!H$10-Revenue!H$13*Assumptions!H$8 | I10: =H10+Revenue!I$13*Assumptions!I$10-Revenue!I$13*Assumptions!I$8 | J10: =I10+Revenue!J$13*Assumptions!J$10-Revenue!J$13*Assumptions!J$8 | K10: =J10+Revenue!K$13*Assumptions!K$10-Revenue!K$13*Assumptions!K$8
A11: Intangible Assets | B11: 20000000 | C11: 20000000 | D11: 20000000 | E11: 20000000 | F11: 20000000 | G11: 20000000 | H11: 20000000 | I11: 20000000 | J11: 20000000 | K11: 20000000
A12: Total Assets | B12: =B9+B10+B11 | C12: =C9+C10+C11 | D12: =D9+D10+D11 | E12: =E9+E10+E11 | F12: =F9+F10+F11 | G12: =G9+G10+G11 | H12: =H9+H10+H11 | I12: =I9+I10+I11 | ... K12: =K9+K10+K11
A14: LIABILITIES & EQUITY
A15: Accounts Payable | B15: =Revenue!B$13*Assumptions!B$11*0.3 | C15: =Revenue!C$13*Assumptions!C$11*0.3 | D15: =Revenue!D$13*Assumptions!D$11*0.3 | E15: =Revenue!E$13*Assumptions!E$11*0.3 | F15: =Revenue!F$13*Assumptions!F$11*0.3 | G15: =Revenue!G$13*Assumptions!G$11*0.3 | H15: =Revenue!H$13*Assumptions!H$11*0.3 | I15: =Revenue!I$13*Assumptions!I$11*0.3 | ... K15: =Revenue!K$13*Assumptions!K$11*0.3
A16: Long-Term Debt | B16: 40000000 | C16: 40000000 | D16: 40000000 | E16: 40000000 | F16: 40000000 | G16: 40000000 | H16: 40000000 | I16: 40000000 | J16: 40000000 | K16: 40000000
A17: Total Liabilities | B17: =B15+B16 | C17: =C15+C16 | D17: =D15+D16 | E17: =E15+E16 | F17: =F15+F16 | G17: =G15+G16 | H17: =H15+H16 | I17: =I15+I16 | ... K17: =K15+K16
A18: Retained Earnings | B18: 30000000 | C18: =B18+'P&L'!C$16*(1-Assumptions!C$16) | D18: =C18+'P&L'!D$16*(1-Assumptions!D$16) | E18: =D18+'P&L'!E$16*(1-Assumptions!E$16) | F18: =E18+'P&L'!F$16*(1-Assumptions!F$16) | G18: =F18+'P&L'!G$16*(1-Assumptions!G$16) | H18: =G18+'P&L'!H$16*(1-Assumptions!H$16) | I18: =H18+'P&L'!I$16*(1-Assumptions!I$16) | J18: =I18+'P&L'!J$16*(1-Assumptions!J$16) | K18: =J18+'P&L'!K$16*(1-Assumptions!K$16)
A19: Total Equity | B19: =B12-B17 | C19: =C12-C17 | D19: =D12-D17 | E19: =E12-E17 | F19: =F12-F17 | G19: =G12-G17 | H19: =H12-H17 | I19: =I12-I17 | ... K19: =K12-K17
A20: Balance Check (should = 0) | B20: =B12-B17-B19 | C20: =C12-C17-C19 | D20: =D12-D17-D19 | E20: =E12-E17-E19 | F20: =F12-F17-F19 | G20: =G12-G17-G19 | H20: =H12-H17-H19 | I20: =I12-I17-I19 | ... K20: =K12-K17-K19

Sheet Cash Flow
A1: CASH FLOW STATEMENT
B3: 2024 | C3: 2025 | D3: 2026 | E3: 2027 | F3: 2028 | G3: 2029 | H3: 2030 | I3: 2031 | J3: 2032 | K3: 2033
A4: OPERATING ACTIVITIES
A5: Net Income | B5: ='P&L'!B$16 | C5: ='P&L'!C$16 | D5: ='P&L'!D$16 | E5: ='P&L'!E$16 | F5: ='P&L'!F$16 | G5: ='P&L'!G$16 | H5: ='P&L'!H$16 | I5: ='P&L'!I$16 | ... K5: ='P&L'!K$16
A6: Add: D&A | B6: =Revenue!B$13*Assumptions!B$8 | C6: =Revenue!C$13*Assumptions!C$8 | D6: =Revenue!D$13*Assumptions!D$8 | E6: =Revenue!E$13*Assumptions!E$8 | F6: =Revenue!F$13*Assumptions!F$8 | G6: =Revenue!G$13*Assumptions!G$8 | H6: =Revenue!H$13*Assumptions!H$8 | I6: =Revenue!I$13*Assumptions!I$8 | ... K6: =Revenue!K$13*Assumptions!K$8
A7: Changes in Working Capital | B7: 0 | C7: =-('Balance Sheet'!C$6-'Balance Sheet'!B$6+'Balance Sheet'!C$7-'Balance Sheet'!B$7-'Balance Sheet'!C$15+'Balance Sheet'!B$15) | D7: =-('Balance Sheet'!D$6-'Balance Sheet'!C$6+'Balance Sheet'!D$7-'Balance Sheet'!C$7-'Balance Sheet'!D$15+'Balance Sheet'!C$15) | E7: =-('Balance Sheet'!E$6-'Balance Sheet'!D$6+'Balance Sheet'!E$7-'Balance Sheet'!D$7-'Balance Sheet'!E$15+'Balance Sheet'!D$15) | F7: =-('Balance Sheet'!F$6-'Balance Sheet'!E$6+'Balance Sheet'!F$7-'Balance Sheet'!E$7-'Balance Sheet'!F$15+'Balance Sheet'!E$15) | G7: =-('Balance Sheet'!G$6-'Balance Sheet'!F$6+'Balance Sheet'!G$7-'Balance Sheet'!F$7-'Balance Sheet'!G$15+'Balance Sheet'!F$15) | H7: =-('Balance Sheet'!H$6-'Balance Sheet'!G$6+'Balance Sheet'!H$7-'Balance Sheet'!G$7-'Balance Sheet'!H$15+'Balance Sheet'!G$15) | I7: =-('Balance Sheet'!I$6-'Balance Sheet'!H$6+'Balance Sheet'!I$7-'Balance Sheet'!H$7-'Balance Sheet'!I$15+'Balance Sheet'!H$15) | J7: =-('Balance Sheet'!J$6-'Balance Sheet'!I$6+'Balance Sheet'!J$7-'Balance Sheet'!I$7-'Balance Sheet'!J$15+'Balance Sheet'!I$15) | K7: =-('Balance Sheet'!K$6-'Balance Sheet'!J$6+'Balance Sheet'!K$7-'Balance Sheet'!J$7-'Balance Sheet'!K$15+'Balance Sheet'!J$15)
A8: Cash from Operations | B8: =B5+B6+B7 | C8: =C5+C6+C7 | D8: =D5+D6+D7 | E8: =E5+E6+E7 | F8: =F5+F6+F7 | G8: =G5+G6+G7 | H8: =H5+H6+H7 | I8: =I5+I6+I7 | ... K8: =K5+K6+K7
A10: INVESTING ACTIVITIES
A11: Capital Expenditures | B11: =-Revenue!B$13*Assumptions!B$10 | C11: =-Revenue!C$13*Assumptions!C$10 | D11: =-Revenue!D$13*Assumptions!D$10 | E11: =-Revenue!E$13*Assumptions!E$10 | F11: =-Revenue!F$13*Assumptions!F$10 | G11: =-Revenue!G$13*Assumptions!G$10 | H11: =-Revenue!H$13*Assumptions!H$10 | I11: =-Revenue!I$13*Assumptions!I$10 | ... K11: =-Revenue!K$13*Assumptions!K$10
A13: FINANCING ACTIVITIES
A14: Dividends Paid | B14: =-'P&L'!B$16*Assumptions!B$16 | C14: =-'P&L'!C$16*Assumptions!C$16 | D14: =-'P&L'!D$16*Assumptions!D$16 | E14: =-'P&L'!E$16*Assumptions!E$16 | F14: =-'P&L'!F$16*Assumptions!F$16 | G14: =-'P&L'!G$16*Assumptions!G$16 | H14: =-'P&L'!H$16*Assumptions!H$16 | I14: =-'P&L'!I$16*Assumptions!I$16 | ... K14: =-'P&L'!K$16*Assumptions!K$16
A16: Net Change in Cash | B16: =B8+B11+B14 | C16: =C8+C11+C14 | D16: =D8+D11+D14 | E16: =E8+E11+E14 | F16: =F8+F11+F14 | G16: =G8+G11+G14 | H16: =H8+H11+H14 | I16: =I8+I11+I14 | ... K16: =K8+K11+K14
A17: Ending Cash Balance | B17: ='Balance Sheet'!B$5+B16 | C17: =B17+C16 | D17: =C17+D16 | E17: =D17+E16 | F17: =E17+F16 | G17: =F17+G16 | H17: =G17+H16 | I17: =H17+I16 | J17: =I17+J16 | K17: =J17+K16

Sheet DCF
A1: DCF VALUATION
B3: 2024 | C3: 2025 | D3: 2026 | E3: 2027 | F3: 2028 | G3: 2029 | H3: 2030 | I3: 2031 | J3: 2032 | K3: 2033
A4: EBIT | B4: ='P&L'!B$10 | C4: ='P&L'!C$10 | D4: ='P&L'!D$10 | E4: ='P&L'!E$10 | F4: ='P&L'!F$10 | G4: ='P&L'!G$10 | H4: ='P&L'!H$10 | I4: ='P&L'!I$10 | ... K4: ='P&L'!K$10
A5: Tax on EBIT | B5: =-B4*Assumptions!B$9 | C5: =-C4*Assumptions!C$9 | D5: =-D4*Assumptions!D$9 | E5: =-E4*Assumptions!E$9 | F5: =-F4*Assumptions!F$9 | G5: =-G4*Assumptions!G$9 | H5: =-H4*Assumptions!H$9 | I5: =-I4*Assumptions!I$9 | ... K5: =-K4*Assumptions!K$9
A6: NOPAT | B6: =B4+B5 | C6: =C4+C5 | D6: =D4+D5 | E6: =E4+E5 | F6: =F4+F5 | G6: =G4+G5 | H6: =H4+H5 | I6: =I4+I5 | ... K6: =K4+K5
A7: Add: D&A | B7: ='Cash Flow'!B$6 | C7: ='Cash Flow'!C$6 | D7: ='Cash Flow'!D$6 | E7: ='Cash Flow'!E$6 | F7: ='Cash Flow'!F$6 | G7: ='Cash Flow'!G$6 | H7: ='Cash Flow'!H$6 | I7: ='Cash Flow'!I$6 | ... K7: ='Cash Flow'!K$6
A8: Less: CapEx | B8: ='Cash Flow'!B$11 | C8: ='Cash Flow'!C$11 | D8: ='Cash Flow'!D$11 | E8: ='Cash Flow'!E$11 | F8: ='Cash Flow'!F$11 | G8: ='Cash Flow'!G$11 | H8: ='Cash Flow'!H$11 | I8: ='Cash Flow'!I$11 | ... K8: ='Cash Flow'!K$11
A9: Less: Change in NWC | B9: ='Cash Flow'!B$7 | C9: ='Cash Flow'!C$7 | D9: ='Cash Flow'!D$7 | E9: ='Cash Flow'!E$7 | F9: ='Cash Flow'!F$7 | G9: ='Cash Flow'!G$7 | H9: ='Cash Flow'!H$7 | I9: ='Cash Flow'!I$7 | ... K9: ='Cash Flow'!K$7
A10: Free Cash Flow (FCFF) | B10: =B6+B7+B8+B9 | C10: =C6+C7+C8+C9 | D10: =D6+D7+D8+D9 | E10: =E6+E7+E8+E9 | F10: =F6+F7+F8+F9 | G10: =G6+G7+G8+G9 | H10: =H6+H7+H8+H9 | I10: =I6+I7+I8+I9 | ... K10: =K6+K7+K8+K9
A12: Discount Factor | B12: =1/(1+Assumptions!B$12)^1 | C12: =1/(1+Assumptions!C$12)^2 | D12: =1/(1+Assumptions!D$12)^3 | E12: =1/(1+Assumptions!E$12)^4 | F12: =1/(1+Assumptions!F$12)^5 | G12: =1/(1+Assumptions!G$12)^6 | H12: =1/(1+Assumptions!H$12)^7 | I12: =1/(1+Assumptions!I$12)^8 | J12: =1/(1+Assumptions!J$12)^9 | K12: =1/(1+Assumptions!K$12)^10
A13: PV of FCF | B13: =B10*B12 | C13: =C10*C12 | D13: =D10*D12 | E13: =E10*E12 | F13: =F10*F12 | G13: =G10*G12 | H13: =H10*H12 | I13: =I10*I12 | ... K13: =K10*K12
A15: VALUATION SUMMARY
A16: Sum of PV of FCFs | B16: =SUM(B13:K13)
A17: Terminal Value (Gordon Growth) | B17: =K10*(1+Assumptions!K$13)/(Assumptions!K$12-Assumptions!K$13)
A18: PV of Terminal Value | B18: =B17*K12
A19: Enterprise Value | B19: =B16+B18
A20: Less: Net Debt | B20: ='Balance Sheet'!B$16-'Balance Sheet'!B$5
A21: Equity Value | B21: =B19-B20
A22: Price per Share | B22: =B21/Assumptions!B$14/1000000

Sheet Sensitivity
A1: SENSITIVITY TABLE: WACC vs Terminal Growth
A2: Enterprise Value at different WACC / TGR combos
A4: WACC \ TGR | B4: 0.01 | C4: 0.015 | D4: 0.02 | E4: 0.025 | F4: 0.03 | G4: 0.035
A5: 0.08 | B5: =DCF!B16+DCF!K10*(1+0.01)/(0.08-0.01)*1/(1+0.08)^10 | C5: =DCF!B16+DCF!K10*(1+0.015)/(0.08-0.015)*1/(1+0.08)^10 | D5: =DCF!B16+DCF!K10*(1+0.02)/(0.08-0.02)*1/(1+0.08)^10 | E5: =DCF!B16+DCF!K10*(1+0.025)/(0.08-0.025)*1/(1+0.08)^10 | F5: =DCF!B16+DCF!K10*(1+0.03)/(0.08-0.03)*1/(1+0.08)^10 | G5: =DCF!B16+DCF!K10*(1+0.035)/(0.08-0.035)*1/(1+0.08)^10
A6: 0.09 | B6: =DCF!B16+DCF!K10*(1+0.01)/(0.09-0.01)*1/(1+0.09)^10 | C6: =DCF!B16+DCF!K10*(1+0.015)/(0.09-0.015)*1/(1+0.09)^10 | D6: =DCF!B16+DCF!K10*(1+0.02)/(0.09-0.02)*1/(1+0.09)^10 | E6: =DCF!B16+DCF!K10*(1+0.025)/(0.09-0.025)*1/(1+0.09)^10 | F6: =DCF!B16+DCF!K10*(1+0.03)/(0.09-0.03)*1/(1+0.09)^10 | G6: =DCF!B16+DCF!K10*(1+0.035)/(0.09-0.035)*1/(1+0.09)^10
A7: 0.1 | B7: =DCF!B16+DCF!K10*(1+0.01)/(0.1-0.01)*1/(1+0.1)^10 | C7: =DCF!B16+DCF!K10*(1+0.015)/(0.1-0.015)*1/(1+0.1)^10 | D7: =DCF!B16+DCF!K10*(1+0.02)/(0.1-0.02)*1/(1+0.1)^10 | E7: =DCF!B16+DCF!K10*(1+0.025)/(0.1-0.025)*1/(1+0.1)^10 | F7: =DCF!B16+DCF!K10*(1+0.03)/(0.1-0.03)*1/(1+0.1)^10 | G7: =DCF!B16+DCF!K10*(1+0.035)/(0.1-0.035)*1/(1+0.1)^10
A8: 0.11 | B8: =DCF!B16+DCF!K10*(1+0.01)/(0.11-0.01)*1/(1+0.11)^10 | C8: =DCF!B16+DCF!K10*(1+0.015)/(0.11-0.015)*1/(1+0.11)^10 | D8: =DCF!B16+DCF!K10*(1+0.02)/(0.11-0.02)*1/(1+0.11)^10 | E8: =DCF!B16+DCF!K10*(1+0.025)/(0.11-0.025)*1/(1+0.11)^10 | F8: =DCF!B16+DCF!K10*(1+0.03)/(0.11-0.03)*1/(1+0.11)^10 | G8: =DCF!B16+DCF!K10*(1+0.035)/(0.11-0.035)*1/(1+0.11)^10
A9: 0.12 | B9: =DCF!B16+DCF!K10*(1+0.01)/(0.12-0.01)*1/(1+0.12)^10 | C9: =DCF!B16+DCF!K10*(1+0.015)/(0.12-0.015)*1/(1+0.12)^10 | D9: =DCF!B16+DCF!K10*(1+0.02)/(0.12-0.02)*1/(1+0.12)^10 | E9: =DCF!B16+DCF!K10*(1+0.025)/(0.12-0.025)*1/(1+0.12)^10 | F9: =DCF!B16+DCF!K10*(1+0.03)/(0.12-0.03)*1/(1+0.12)^10 | G9: =DCF!B16+DCF!K10*(1+0.035)/(0.12-0.035)*1/(1+0.12)^10

Sheet Headcount
A1: HEADCOUNT PLAN
B3: 2024 | C3: 2025 | D3: 2026 | E3: 2027 | F3: 2028 | G3: 2029 | H3: 2030 | I3: 2031 | J3: 2032 | K3: 2033
A4: Engineering | B4: 120 | C4: =ROUND(B4*(1+Assumptions!C$4*0.7),0) | D4: =ROUND(C4*(1+Assumptions!D$4*0.7),0) | E4: =ROUND(D4*(1+Assumptions!E$4*0.7),0) | F4: =ROUND(E4*(1+Assumptions!F$4*0.7),0) | G4: =ROUND(F4*(1+Assumptions!G$4*0.7),0) | H4: =ROUND(G4*(1+Assumptions!H$4*0.7),0) | I4: =ROUND(H4*(1+Assumptions!I$4*0.7),0) | J4: =ROUND(I4*(1+Assumptions!J$4*0.7),0) | K4: =ROUND(J4*(1+Assumptions!K$4*0.7),0)
A5: Sales | B5: 80 | C5: =ROUND(B5*(1+Assumptions!C$4*0.7),0) | D5: =ROUND(C5*(1+Assumptions!D$4*0.7),0) | E5: =ROUND(D5*(1+Assumptions!E$4*0.7),0) | F5: =ROUND(E5*(1+Assumptions!F$4*0.7),0) | G5: =ROUND(F5*(1+Assumptions!G$4*0.7),0) | H5: =ROUND(G5*(1+Assumptions!H$4*0.7),0) | I5: =ROUND(H5*(1+Assumptions!I$4*0.7),0) | J5: =ROUND(I5*(1+Assumptions!J$4*0.7),0) | K5: =ROUND(J5*(1+Assumptions!K$4*0.7),0)
A6: Marketing | B6: 40 | C6: =ROUND(B6*(1+Assumptions!C$4*0.7),0) | D6: =ROUND(C6*(1+Assumptions!D$4*0.7),0) | E6: =ROUND(D6*(1+Assumptions!E$4*0.7),0) | F6: =ROUND(E6*(1+Assumptions!F$4*0.7),0) | G6: =ROUND(F6*(1+Assumptions!G$4*0.7),0) | H6: =ROUND(G6*(1+Assumptions!H$4*0.7),0) | I6: =ROUND(H6*(1+Assumptions!I$4*0.7),0) | J6: =ROUND(I6*(1+Assumptions!J$4*0.7),0) | K6: =ROUND(J6*(1+Assumptions!K$4*0.7),0)
A7: Customer Success | B7: 35 | C7: =ROUND(B7*(1+Assumptions!C$4*0.7),0) | D7: =ROUND(C7*(1+Assumptions!D$4*0.7),0) | E7: =ROUND(D7*(1+Assumptions!E$4*0.7),0) | F7: =ROUND(E7*(1+Assumptions!F$4*0.7),0) | G7: =ROUND(F7*(1+Assumptions!G$4*0.7),0) | H7: =ROUND(G7*(1+Assumptions!H$4*0.7),0) | I7: =ROUND(H7*(1+Assumptions!I$4*0.7),0) | J7: =ROUND(I7*(1+Assumptions!J$4*0.7),0) | K7: =ROUND(J7*(1+Assumptions!K$4*0.7),0)
A8: Finance & Accounting | B8: 20 | C8: =ROUND(B8*(1+Assumptions!C$4*0.7),0) | D8: =ROUND(C8*(1+Assumptions!D$4*0.7),0) | E8: =ROUND(D8*(1+Assumptions!E$4*0.7),0) | F8: =ROUND(E8*(1+Assumptions!F$4*0.7),0) | G8: =ROUND(F8*(1+Assumptions!G$4*0.7),0) | H8: =ROUND(G8*(1+Assumptions!H$4*0.7),0) | I8: =ROUND(H8*(1+Assumptions!I$4*0.7),0) | J8: =ROUND(I8*(1+Assumptions!J$4*0.7),0) | K8: =ROUND(J8*(1+Assumptions!K$4*0.7),0)
A9: HR & Admin | B9: 15 | C9: =ROUND(B9*(1+Assumptions!C$4*0.7),0) | D9: =ROUND(C9*(1+Assumptions!D$4*0.7),0) | E9: =ROUND(D9*(1+Assumptions!E$4*0.7),0) | F9: =ROUND(E9*(1+Assumptions!F$4*0.7),0) | G9: =ROUND(F9*(1+Assumptions!G$4*0.7),0) | H9: =ROUND(G9*(1+Assumptions!H$4*0.7),0) | I9: =ROUND(H9*(1+Assumptions!I$4*0.7),0) | J9: =ROUND(I9*(1+Assumptions!J$4*0.7),0) | K9: =ROUND(J9*(1+Assumptions!K$4*0.7),0)
A10: Legal | B10: 8 | C10: =ROUND(B10*(1+Assumptions!C$4*0.7),0) | D10: =ROUND(C10*(1+Assumptions!D$4*0.7),0) | E10: =ROUND(D10*(1+Assumptions!E$4*0.7),0) | F10: =ROUND(E10*(1+Assumptions!F$4*0.7),0) | G10: =ROUND(F10*(1+Assumptions!G$4*0.7),0) | H10: =ROUND(G10*(1+Assumptions!H$4*0.7),0) | I10: =ROUND(H10*(1+Assumptions!I$4*0.7),0) | J10: =ROUND(I10*(1+Assumptions!J$4*0.7),0) | K10: =ROUND(J10*(1+Assumptions!K$4*0.7),0)
A11: Executive | B11: 10 | C11: =ROUND(B11*(1+Assumptions!C$4*0.7),0) | D11: =ROUND(C11*(1+Assumptions!D$4*0.7),0) | E11: =ROUND(D11*(1+Assumptions!E$4*0.7),0) | F11: =ROUND(E11*(1+Assumptions!F$4*0.7),0) | G11: =ROUND(F11*(1+Assumptions!G$4*0.7),0) | H11: =ROUND(G11*(1+Assumptions!H$4*0.7),0) | I11: =ROUND(H11*(1+Assumptions!I$4*0.7),0) | J11: =ROUND(I11*(1+Assumptions!J$4*0.7),0) | K11: =ROUND(J11*(1+Assumptions!K$4*0.7),0)
A12: Data Science | B12: 25 | C12: =ROUND(B12*(1+Assumptions!C$4*0.7),0) | D12: =ROUND(C12*(1+Assumptions!D$4*0.7),0) | E12: =ROUND(D12*(1+Assumptions!E$4*0.7),0) | F12: =ROUND(E12*(1+Assumptions!F$4*0.7),0) | G12: =ROUND(F12*(1+Assumptions!G$4*0.7),0) | H12: =ROUND(G12*(1+Assumptions!H$4*0.7),0) | I12: =ROUND(H12*(1+Assumptions!I$4*0.7),0) | J12: =ROUND(I12*(1+Assumptions!J$4*0.7),0) | K12: =ROUND(J12*(1+Assumptions!K$4*0.7),0)
A13: Product Management | B13: 18 | C13: =ROUND(B13*(1+Assumptions!C$4*0.7),0) | D13: =ROUND(C13*(1+Assumptions!D$4*0.7),0) | E13: =ROUND(D13*(1+Assumptions!E$4*0.7),0) | F13: =ROUND(E13*(1+Assumptions!F$4*0.7),0) | G13: =ROUND(F13*(1+Assumptions!G$4*0.7),0) | H13: =ROUND(G13*(1+Assumptions!H$4*0.7),0) | I13: =ROUND(H13*(1+Assumptions!I$4*0.7),0) | J13: =ROUND(I13*(1+Assumptions!J$4*0.7),0) | K13: =ROUND(J13*(1+Assumptions!K$4*0.7),0)
A14: DevOps / SRE | B14: 15 | C14: =ROUND(B14*(1+Assumptions!C$4*0.7),0) | D14: =ROUND(C14*(1+Assumptions!D$4*0.7),0) | E14: =ROUND(D14*(1+Assumptions!E$4*0.7),0) | F14: =ROUND(E14*(1+Assumptions!F$4*0.7),0) | G14: =ROUND(F14*(1+Assumptions!G$4*0.7),0) | H14: =ROUND(G14*(1+Assumptions!H$4*0.7),0) | I14: =ROUND(H14*(1+Assumptions!I$4*0.7),0) | J14: =ROUND(I14*(1+Assumptions!J$4*0.7),0) | K14: =ROUND(J14*(1+Assumptions!K$4*0.7),0)
A15: Quality Assurance | B15: 20 | C15: =ROUND(B15*(1+Assumptions!C$4*0.7),0) | D15: =ROUND(C15*(1+Assumptions!D$4*0.7),0) | E15: =ROUND(D15*(1+Assumptions!E$4*0.7),0) | F15: =ROUND(E15*(1+Assumptions!F$4*0.7),0) | G15: =ROUND(F15*(1+Assumptions!G$4*0.7),0) | H15: =ROUND(G15*(1+Assumptions!H$4*0.7),0) | I15: =ROUND(H15*(1+Assumptions!I$4*0.7),0) | J15: =ROUND(I15*(1+Assumptions!J$4*0.7),0) | K15: =ROUND(J15*(1+Assumptions!K$4*0.7),0)
A17: Total Headcount | B17: =SUM(B4:B15) | C17: =SUM(C4:C15) | D17: =SUM(D4:D15) | E17: =SUM(E4:E15) | F17: =SUM(F4:F15) | G17: =SUM(G4:G15) | H17: =SUM(H4:H15) | I17: =SUM(I4:I15) | ... K17: =SUM(K4:K15)
A18: Revenue per Employee | B18: =Revenue!B$13/B17 | C18: =Revenue!C$13/C17 | D18: =Revenue!D$13/D17 | E18: =Revenue!E$13/E17 | F18: =Revenue!F$13/F17 | G18: =Revenue!G$13/G17 | H18: =Revenue!H$13/H17 | I18: =Revenue!I$13/I17 | ... K18: =Revenue!K$13/K17

Sheet KPIs
A1: KEY PERFORMANCE INDICATORS
B3: 2024 | C3: 2025 | D3: 2026 | E3: 2027 | F3: 2028 | G3: 2029 | H3: 2030 | I3: 2031 | J3: 2032 | K3: 2033
A4: Revenue | B4: =Revenue!B$13 | C4: =Revenue!C$13 | D4: =Revenue!D$13 | E4: =Revenue!E$13 | F4: =Revenue!F$13 | G4: =Revenue!G$13 | H4: =Revenue!H$13 | I4: =Revenue!I$13 | ... K4: =Revenue!K$13
A5: Revenue Growth YoY | B5: N/A | C5: =(C4-B4)/B4 | D5: =(D4-C4)/C4 | E5: =(E4-D4)/D4 | F5: =(F4-E4)/E4 | G5: =(G4-F4)/F4 | H5: =(H4-G4)/G4 | I5: =(I4-H4)/H4 | J5: =(J4-I4)/I4 | K5: =(K4-J4)/J4
A6: Gross Margin | B6: ='P&L'!B$7 | C6: ='P&L'!C$7 | D6: ='P&L'!D$7 | E6: ='P&L'!E$7 | F6: ='P&L'!F$7 | G6: ='P&L'!G$7 | H6: ='P&L'!H$7 | I6: ='P&L'!I$7 | ... K6: ='P&L'!K$7
A7: EBIT Margin | B7: ='P&L'!B$11 | C7: ='P&L'!C$11 | D7: ='P&L'!D$11 | E7: ='P&L'!E$11 | F7: ='P&L'!F$11 | G7: ='P&L'!G$11 | H7: ='P&L'!H$11 | I7: ='P&L'!I$11 | ... K7: ='P&L'!K$11
A8: Net Margin | B8: ='P&L'!B$17 | C8: ='P&L'!C$17 | D8: ='P&L'!D$17 | E8: ='P&L'!E$17 | F8: ='P&L'!F$17 | G8: ='P&L'!G$17 | H8: ='P&L'!H$17 | I8: ='P&L'!I$17 | ... K8: ='P&L'!K$17
A9: EPS | B9: ='P&L'!B$19 | C9: ='P&L'!C$19 | D9: ='P&L'!D$19 | E9: ='P&L'!E$19 | F9: ='P&L'!F$19 | G9: ='P&L'!G$19 | H9: ='P&L'!H$19 | I9: ='P&L'!I$19 | ... K9: ='P&L'!K$19
A10: Free Cash Flow | B10: =DCF!B$10 | C10: =DCF!C$10 | D10: =DCF!D$10 | E10: =DCF!E$10 | F10: =DCF!F$10 | G10: =DCF!G$10 | H10: =DCF!H$10 | I10: =DCF!I$10 | ... K10: =DCF!K$10
A11: Cash Balance | B11: ='Balance Sheet'!B$5 | C11: ='Balance Sheet'!C$5 | D11: ='Balance Sheet'!D$5 | E11: ='Balance Sheet'!E$5 | F11: ='Balance Sheet'!F$5 | G11: ='Balance Sheet'!G$5 | H11: ='Balance Sheet'!H$5 | I11: ='Balance Sheet'!I$5 | ... K11: ='Balance Sheet'!K$5
A12: Total Debt | B12: ='Balance Sheet'!B$16 | C12: ='Balance Sheet'!C$16 | D12: ='Balance Sheet'!D$16 | E12: ='Balance Sheet'!E$16 | F12: ='Balance Sheet'!F$16 | G12: ='Balance Sheet'!G$16 | H12: ='Balance Sheet'!H$16 | I12: ='Balance Sheet'!I$16 | ... K12: ='Balance Sheet'!K$16
A13: Debt/Equity | B13: ='Balance Sheet'!B$16/'Balance Sheet'!B$19 | C13: ='Balance Sheet'!C$16/'Balance Sheet'!C$19 | D13: ='Balance Sheet'!D$16/'Balance Sheet'!D$19 | E13: ='Balance Sheet'!E$16/'Balance Sheet'!E$19 | F13: ='Balance Sheet'!F$16/'Balance Sheet'!F$19 | G13: ='Balance Sheet'!G$16/'Balance Sheet'!G$19 | H13: ='Balance Sheet'!H$16/'Balance Sheet'!H$19 | I13: ='Balance Sheet'!I$16/'Balance Sheet'!I$19 | ... K13: ='Balance Sheet'!K$16/'Balance Sheet'!K$19
